[
    {
        "addressLine1": "16112 Crabbs Branch Way",
        "city": "Derwood",
        "state": "MD",
        "zipCode": "20855",
        "formattedAddress": "16112 Crabbs Branch Way, Apt 11, Derwood, MD 20855",
        "addressLine2": "Apt 11",
        "features": {},
        "county": "Montgomery",
        "id": "16112-Crabbs-Branch-Way,-Apt-11,-Derwood,-MD-20855",
        "longitude": -77.156909,
        "latitude": 39.118854
    },
    {
        "addressLine1": "914 Collier Rd NW",
        "city": "Atlanta",
        "state": "GA",
        "zipCode": "30318",
        "formattedAddress": "914 Collier Rd NW, Apt 3330, Atlanta, GA 30318",
        "addressLine2": "Apt 3330",
        "county": "Fulton",
        "propertyType": "Apartment",
        "bedrooms": 2,
        "bathrooms": 2,
        "squareFootage": 1032,
        "features": {},
        "id": "914-Collier-Rd-NW,-Apt-3330,-Atlanta,-GA-30318",
        "longitude": -84.415953,
        "latitude": 33.80869
    },
    {
        "addressLine1": "11990 Prairie Ln",
        "city": "Lusby",
        "state": "MD",
        "zipCode": "20657",
        "formattedAddress": "11990 Prairie Ln, Lusby, MD 20657",
        "bedrooms": 3,
        "squareFootage": 1714,
        "yearBuilt": 2006,
        "features": {
            "architectureType": "Conventional",
            "cooling": true,
            "coolingType": "Commercial",
            "exteriorType": "Aluminum / Vinyl Siding",
            "fireplace": true,
            "fireplaceType": "Gas Log",
            "floorCount": 2,
            "garage": true,
            "garageSpaces": 2,
            "garageType": "Attached Garage",
            "heating": true,
            "heatingType": "Heat Pump",
            "roofType": "Composition Shingle",
            "unitCount": 1
        },
        "county": "Calvert",
        "assessorID": "01-093894",
        "legalDescription": "LT 19 SEC 1F CHES RANCH ESTS",
        "subdivision": "CHES RANCH ESTATES",
        "zoning": "R",
        "ownerOccupied": true,
        "bathrooms": 2.5,
        "propertyType": "Single Family",
        "taxAssessment": {
            "2022": {
                "value": 241767
            }
        },
        "propertyTaxes": {
            "2022": {
                "total": 2512
            }
        },
        "lastSalePrice": 339900,
        "lastSaleDate": "2006-05-30T00:00:00.000Z",
        "owner": {
            "names": [
                "TAMMY Z BELISARIO"
            ],
            "mailingAddress": {
                "id": "11990-Prairie-Ln,-Lusby,-MD-20657",
                "addressLine1": "11990 Prairie Ln",
                "city": "Lusby",
                "state": "MD",
                "zipCode": "20657"
            }
        },
        "id": "11990-Prairie-Ln,-Lusby,-MD-20657",
        "longitude": -76.426234,
        "latitude": 38.356525
    },
    {
        "addressLine1": "1310 Ashville Rd",
        "city": "Leeds",
        "state": "AL",
        "zipCode": "35094",
        "formattedAddress": "1310 Ashville Rd, Leeds, AL 35094",
        "bedrooms": 3,
        "squareFootage": 1398,
        "county": "Jefferson",
        "propertyType": "Single Family",
        "features": {},
        "id": "1310-Ashville-Rd,-Leeds,-AL-35094",
        "longitude": -86.535094,
        "latitude": 33.553497
    },
    {
        "addressLine1": "216 N Apple St",
        "city": "Hamburg",
        "state": "PA",
        "zipCode": "19526",
        "formattedAddress": "216 N Apple St, Apt 1, Hamburg, PA 19526",
        "addressLine2": "Apt 1",
        "county": "Berks",
        "features": {},
        "id": "216-N-Apple-St,-Apt-1,-Hamburg,-PA-19526",
        "longitude": -75.984661,
        "latitude": 40.559012
    }
]